[
  {"data": { "label": "my_tasks", "icon": "tasks", "url": ""},
    "children": [
      { "data": { "label": "inbox", "icon": "inbox", "url": "/inbox" }},
      { "data": { "label": "outbox", "icon": "paper-plane-o", "url": "/outbox" }}
    ]
  },
  { "data": { "label": "my_documents", "icon": "briefcase", "url": ""},
    "children": [
      { "data": { "label": "draft", "icon": "file", "url": "/draft" }},
      { "data": { "label": "in_progress", "icon": "spinner", "url": "/inprogress" }},
      { "data": { "label": "completed", "icon": "check", "url": "/completed" }}
    ]
  },
  { "data": { "label": "requests", "icon": "copy", "url": "" },
    "children": [
      { "data": { "label": "request1", "icon": "file-o", "url": "/request1" }},
      { "data": { "label": "request2", "icon": "file-o", "url": "/request2" }},
      { "data": { "label": "request3", "icon": "file-o", "url": "/request3" }}
    ]
  },
  { "data": { "label": "modules", "icon": "cubes", "url": "" },
    "children": [
      { "data": { "label": "module1", "icon": "cube", "url": "/module1" }},
      { "data": { "label": "module2", "icon": "cube", "url": "/module2" }},
      { "data": { "label": "module3", "icon": "cube", "url": "/module3" }}
    ]
  },
  { "data": { "label": "master_data", "icon": "database", "url": "" },
    "children": [
      { "data": { "label": "masterdata1", "icon": "circle-o", "url": "/md1" }},
      { "data": { "label": "masterdata2", "icon": "circle-o", "url": "/md2" }},
      { "data": { "label": "masterdata3", "icon": "circle-o", "url": "/md3" }}
    ]
  },
  { "data": { "label": "settings", "icon": "cogs", "url": "" },
    "children": [
      { "data": { "label": "setting1", "icon": "cog", "url": "/setting1" }},
      { "data": { "label": "setting1", "icon": "cog", "url": "/setting2" }},
      { "data": { "label": "setting1", "icon": "cog", "url": "/setting3" }}
    ]
  },
  { "data": { "label": "application", "icon": "desktop", "url": "" },
    "children": [
      { "data": { "label": "about", "icon": "info-circle", "url": "/about" }},
      { "data": { "label": "profile", "icon": "user-circle", "url": "/profile" }},
      { "data": { "label": "policy", "icon": "universal-access", "url": "/policy" }},
      { "data": { "label": "maintenance", "icon": "wrench", "url": "/maintenance" }},
      { "data": { "label": "my_favourites", "icon": "heart", "url": "/fav" }},
      { "data": { "label": "themes", "icon": "paint-brush", "url": "/theme" }},
      { "data": { "label": "settings", "icon": "cogs", "url": "/setting" }},
      { "data": { "label": "lock_system", "icon": "lock", "url": "/lockscreen" }},
      { "data": { "label": "logout", "icon": "sign-out", "url": "/login" }}
    ]
  }
]
